<?xml version="1.0" encoding="UTF-8"?>
<?xml-model href="ej2.xsd" type="application/xml" schematypens="http://www.w3.org/2001/XMLSchema"?>
    <shiporder orderid="3">
        <orderperson></orderperson>
        <shipto>
            <name></name>
            <address></address>
            <city></city>
            <country></country>
        </shipto>
        <item>
            <title></title>
            <note></note>
            <quantity>5</quantity>
            <price>2.2</price>
        </item>
    </shiporder>